README.md
setup.py
nebula/AsyncClient.py
nebula/Client.py
nebula/Common.py
nebula/ConnectionPool.py
nebula/__init__.py
nebula/common/__init__.py
nebula/common/constants.py
nebula/common/ttypes.py
nebula/fbthrift/TMultiplexedProcessor.py
nebula/fbthrift/TSCons.py
nebula/fbthrift/Thrift.py
nebula/fbthrift/__init__.py
nebula/fbthrift/protocol/TBinaryProtocol.py
nebula/fbthrift/protocol/TCompactProtocol.py
nebula/fbthrift/protocol/THeaderProtocol.py
nebula/fbthrift/protocol/TJSONProtocol.py
nebula/fbthrift/protocol/TMultiplexedProtocol.py
nebula/fbthrift/protocol/TProtocol.py
nebula/fbthrift/protocol/TProtocolDecorator.py
nebula/fbthrift/protocol/TSimpleJSONProtocol.py
nebula/fbthrift/protocol/__init__.py
nebula/fbthrift/server/TAsyncioServer.py
nebula/fbthrift/server/TCppServer.py
nebula/fbthrift/server/TGeventServer.py
nebula/fbthrift/server/TNonblockingServer.py
nebula/fbthrift/server/TServer.py
nebula/fbthrift/server/TTrolliusServer.py
nebula/fbthrift/server/__init__.py
nebula/fbthrift/transport/TFuzzyHeaderTransport.py
nebula/fbthrift/transport/THeaderTransport.py
nebula/fbthrift/transport/THttpClient.py
nebula/fbthrift/transport/TSSLSocket.py
nebula/fbthrift/transport/TSSLSocketOverHttpTunnel.py
nebula/fbthrift/transport/TSocket.py
nebula/fbthrift/transport/TSocketOverHttpTunnel.py
nebula/fbthrift/transport/TSocketTest.py
nebula/fbthrift/transport/TTransport.py
nebula/fbthrift/transport/TTwisted.py
nebula/fbthrift/transport/__init__.py
nebula/fbthrift/util/BytesStrIO.py
nebula/fbthrift/util/Decorators.py
nebula/fbthrift/util/Recursive.py
nebula/fbthrift/util/Serializer.py
nebula/fbthrift/util/TCppServerTestManager.py
nebula/fbthrift/util/TCppServerTestManagerTest.py
nebula/fbthrift/util/TValidator.py
nebula/fbthrift/util/__init__.py
nebula/fbthrift/util/async_common.py
nebula/fbthrift/util/asyncio.py
nebula/fbthrift/util/fuzzer.py
nebula/fbthrift/util/randomizer.py
nebula/fbthrift/util/remote.py
nebula/fbthrift/util/trollius.py
nebula/graph/AsyncGraphService.py
nebula_python.egg-info/PKG-INFO
nebula_python.egg-info/SOURCES.txt
nebula_python.egg-info/dependency_links.txt
nebula_python.egg-info/requires.txt
nebula_python.egg-info/top_level.txt