Metadata-Version: 1.0
Name: nebula-python
Version: 1.1.1.post1
Summary: Python client for Nebula Graph
Home-page: https://github.com/vesoft-inc/nebula-python
Author: darion.wang
Author-email: darion.wang@vesoft-inc.com
License: Apache 2.0 + Common Clause 1.0
Platform: 2.7, 3.5, 3.7
